adaptive_power_neurons/__init__.py
adaptive_power_neurons/activation.py
adaptive_power_neurons/adaptive_power_model.py
adaptive_power_neurons/adaptive_power_neurons.py
adaptive_power_neurons/dense_layer.py
adaptive_power_neurons/optimizer.py
adaptive_power_neurons-0.4.0.dist-info/LICENSE
adaptive_power_neurons-0.4.0.dist-info/METADATA
adaptive_power_neurons-0.4.0.dist-info/WHEEL
adaptive_power_neurons-0.4.0.dist-info/entry_points.txt
adaptive_power_neurons-0.4.0.dist-info/top_level.txt
adaptive_power_neurons-0.4.0.dist-info/RECORD
