Metadata-Version: 2.1
Name: adaptive-power-neurons
Version: 0.4.0
Summary: A neural network model using adaptive power neurons for regression and classification
Home-page: https://github.com/Dedeep007/adaptive-power-neurons
Author: Dedeep Vasireddy
Author-email: vasireddydedeep@gmail.com
License: UNKNOWN
Project-URL: Documentation, https://github.com/Dedeep007/adaptive-power-neurons/wiki
Project-URL: Source, https://github.com/Dedeep007/adaptive-power-neurons
Keywords: neural network,regression,adaptive power neurons,machine learning
Platform: UNKNOWN
Classifier: Development Status :: 3 - Alpha
Classifier: Intended Audience :: Developers
Classifier: License :: OSI Approved :: MIT License
Classifier: Programming Language :: Python :: 3
Classifier: Programming Language :: Python :: 3.8
Classifier: Programming Language :: Python :: 3.9
Classifier: Programming Language :: Python :: 3.10
Classifier: Programming Language :: Python :: 3.11
Requires-Python: >=3.6
Requires-Dist: numpy>=1.18.5
Requires-Dist: scikit-learn>=0.23.1
Provides-Extra: dev
Requires-Dist: pytest>=5.4; extra == "dev"
Requires-Dist: sphinx>=3.0; extra == "dev"
